synsense_samna/__init__.py
synsense_samna/auto_upgrade.py
synsense_samna-0.9.23.0.data/scripts/samna-upgrade
synsense_samna-0.9.23.0.dist-info/METADATA
synsense_samna-0.9.23.0.dist-info/WHEEL
synsense_samna-0.9.23.0.dist-info/top_level.txt
synsense_samna-0.9.23.0.dist-info/RECORD
