Metadata-Version: 2.1
Name: synsense-samna
Version: 0.9.23.0
Summary: SynSense Samna Public Package
Home-page: https://synsense.ai/
Author: SynSense
Author-email: carsten.nielsen@synsense.ai
License: UNKNOWN
Platform: UNKNOWN
